geemap/__init__.py
geemap/ai.py
geemap/basemaps.py
geemap/cartoee.py
geemap/chart.py
geemap/cli.py
geemap/colormaps.py
geemap/common.py
geemap/conversion.py
geemap/core.py
geemap/coreutils.py
geemap/datasets.py
geemap/deck.py
geemap/ee_tile_layers.py
geemap/foliumap.py
geemap/geemap.py
geemap/kepler.py
geemap/legends.py
geemap/map_widgets.py
geemap/maplibregl.py
geemap/ml.py
geemap/osm.py
geemap/plot.py
geemap/plotlymap.py
geemap/report.py
geemap/timelapse.py
geemap/toolbar.py
geemap/data/census_data.json
geemap/data/gee_f.json
geemap/data/fonts/alibaba.otf
geemap/data/fonts/arial.ttf
geemap/data/javascripts/ClippedComposite.js
geemap/data/javascripts/FromName.js
geemap/data/javascripts/ModisQaBands.js
geemap/data/javascripts/NormalizedDifference.js
geemap/data/javascripts/QualityMosaic.js
geemap/data/python/javascript_to_python.py
geemap/data/template/NLCD.qml
geemap/data/template/ee_api_docs.csv
geemap/data/template/ee_api_docs.html
geemap/data/template/ee_data_catalog.csv
geemap/data/template/ee_legend_table.txt
geemap/data/template/legend.html
geemap/data/template/legend.txt
geemap/data/template/legend_style.html
geemap/data/template/template.py
geemap/data/template/toolbox.csv
geemap/examples/__init__.py
geemap/examples/datasets.txt
geemap-0.35.1.dist-info/LICENSE
geemap-0.35.1.dist-info/METADATA
geemap-0.35.1.dist-info/WHEEL
geemap-0.35.1.dist-info/entry_points.txt
geemap-0.35.1.dist-info/top_level.txt
geemap-0.35.1.dist-info/RECORD
