Metadata-Version: 2.1
Name: geemap
Version: 0.35.1
Summary: A Python package for interactive mapping using Google Earth Engine and ipyleaflet
Author-email: Qiusheng Wu <giswqs@gmail.com>
License: MIT
Project-URL: Homepage, https://github.com/gee-community/geemap
Keywords: geemap
Classifier: Intended Audience :: Developers
Classifier: License :: OSI Approved :: MIT License
Classifier: Natural Language :: English
Classifier: Programming Language :: Python :: 3.9
Classifier: Programming Language :: Python :: 3.10
Classifier: Programming Language :: Python :: 3.11
Classifier: Programming Language :: Python :: 3.12
Classifier: Programming Language :: Python :: 3.13
Requires-Python: >=3.9
License-File: LICENSE
Requires-Dist: bqplot
Requires-Dist: colour
Requires-Dist: earthengine-api>=1.0.0
Requires-Dist: eerepr>=0.0.4
Requires-Dist: folium>=0.17.0
Requires-Dist: geocoder
Requires-Dist: ipyevents
Requires-Dist: ipyfilechooser>=0.6.0
Requires-Dist: ipyleaflet>=0.19.2
Requires-Dist: ipytree
Requires-Dist: matplotlib
Requires-Dist: numpy
Requires-Dist: pandas
Requires-Dist: plotly
Requires-Dist: pyperclip
Requires-Dist: pyshp>=2.3.1
Requires-Dist: python-box
Requires-Dist: scooby
Provides-Extra: all
Requires-Dist: geemap[ai,apps,backends,extra,lidar,maplibre,raster,sql,vector,workshop]; extra == "all"
Provides-Extra: ai
Requires-Dist: google-api-core; extra == "ai"
Requires-Dist: google-cloud-storage; extra == "ai"
Requires-Dist: google-generativeai; extra == "ai"
Requires-Dist: google_cloud_aiplatform; extra == "ai"
Requires-Dist: langchain-community; extra == "ai"
Requires-Dist: langchain_google_genai; extra == "ai"
Requires-Dist: langchain; extra == "ai"
Requires-Dist: iso8601; extra == "ai"
Provides-Extra: backends
Requires-Dist: keplergl; extra == "backends"
Requires-Dist: pydeck; extra == "backends"
Provides-Extra: extra
Requires-Dist: ee_extra>=0.0.15; extra == "extra"
Requires-Dist: ffmpeg-python; extra == "extra"
Requires-Dist: gdown; extra == "extra"
Requires-Dist: geeadd>=0.5.1; extra == "extra"
Requires-Dist: geojson; extra == "extra"
Requires-Dist: geopandas; extra == "extra"
Requires-Dist: ipynb-py-convert; extra == "extra"
Requires-Dist: jupyterlab>=3; extra == "extra"
Requires-Dist: mapclassify>=2.4.0; extra == "extra"
Requires-Dist: mss; extra == "extra"
Requires-Dist: oeel; extra == "extra"
Requires-Dist: owslib; extra == "extra"
Requires-Dist: palettable; extra == "extra"
Requires-Dist: pycrs; extra == "extra"
Requires-Dist: sankee>=0.1.0; extra == "extra"
Requires-Dist: whiteboxgui>=0.6.0; extra == "extra"
Requires-Dist: xee; extra == "extra"
Provides-Extra: lidar
Requires-Dist: ipygany; extra == "lidar"
Requires-Dist: ipyvtklink; extra == "lidar"
Requires-Dist: laspy[lazrs]; extra == "lidar"
Requires-Dist: panel; extra == "lidar"
Requires-Dist: pyntcloud[LAS]; extra == "lidar"
Requires-Dist: pyvista; extra == "lidar"
Requires-Dist: pyvista-xarray; extra == "lidar"
Requires-Dist: rioxarray; extra == "lidar"
Provides-Extra: raster
Requires-Dist: geedim; extra == "raster"
Requires-Dist: localtileserver>=0.10.1; extra == "raster"
Requires-Dist: rio-cogeo; extra == "raster"
Requires-Dist: rioxarray; extra == "raster"
Requires-Dist: netcdf4; extra == "raster"
Requires-Dist: pyvista-xarray; extra == "raster"
Provides-Extra: sql
Requires-Dist: psycopg2; extra == "sql"
Requires-Dist: sqlalchemy; extra == "sql"
Provides-Extra: apps
Requires-Dist: gradio; extra == "apps"
Requires-Dist: streamlit-folium; extra == "apps"
Requires-Dist: voila; extra == "apps"
Requires-Dist: solara; extra == "apps"
Provides-Extra: vector
Requires-Dist: geopandas; extra == "vector"
Requires-Dist: osmnx; extra == "vector"
Provides-Extra: workshop
Requires-Dist: geopandas; extra == "workshop"
Requires-Dist: geedim; extra == "workshop"
Requires-Dist: ffmpeg-python; extra == "workshop"
Requires-Dist: gdown; extra == "workshop"
Provides-Extra: maplibre
Requires-Dist: geopandas; extra == "maplibre"
Requires-Dist: h3; extra == "maplibre"
Requires-Dist: ipyvuetify; extra == "maplibre"
Requires-Dist: localtileserver; extra == "maplibre"
Requires-Dist: mapclassify; extra == "maplibre"
Requires-Dist: maplibre; extra == "maplibre"
Requires-Dist: pmtiles; extra == "maplibre"
Requires-Dist: rioxarray; extra == "maplibre"
Requires-Dist: xarray; extra == "maplibre"
